tokyo_stock_exchange/__init__.py
tokyo_stock_exchange/tse.csv
tokyo_stock_exchange/tse.py
tokyo_stock_exchange/tse20240229.csv
tokyo_stock_exchange-0.0.3.dist-info/LICENSE
tokyo_stock_exchange-0.0.3.dist-info/METADATA
tokyo_stock_exchange-0.0.3.dist-info/WHEEL
tokyo_stock_exchange-0.0.3.dist-info/top_level.txt
tokyo_stock_exchange-0.0.3.dist-info/RECORD
