Metadata-Version: 2.1
Name: tokyo-stock-exchange
Version: 0.0.3
Summary: A Python library for accessing Tokyo Stock Exchange data.
Author: AKB428
Author-email: AKB428 <otoraru@gmail.com>
Project-URL: Homepage, https://github.com/AKB428/tokyo-stock-exchange
Project-URL: Issues, https://github.com/AKB428/tokyo-stock-exchange/issues
Classifier: Programming Language :: Python :: 3
Classifier: License :: OSI Approved :: MIT License
Classifier: Operating System :: OS Independent
Requires-Python: >=3.8
License-File: LICENSE
Requires-Dist: pandas
